beautylog/__init__.py
beautylog/functions.py
beautylog-0.1.5.dist-info/METADATA
beautylog-0.1.5.dist-info/RECORD
beautylog-0.1.5.dist-info/WHEEL
beautylog-0.1.5.dist-info/top_level.txt
